echarts_china_counties_pypkg
