Metadata-Version: 1.1
Name: echarts-china-counties-pypkg
Version: 0.0.1
Summary: pyecharts map extension - china counties - python package
Home-page: https://github.com/pyecharts/echarts-china-counties-pypkg
Author: pyecharts dev team
Author-email: wangc_2011@hotmail.com
License: Custom
Download-URL: https://github.com/pyecharts/echarts-china-counties-pypkg/archive/0.0.1.tar.gz
Keywords: python
Platform: UNKNOWN
Classifier: Topic :: Office/Business
Classifier: Topic :: Utilities
Classifier: Topic :: Software Development :: Libraries
Classifier: Programming Language :: Python
Classifier: Intended Audience :: Developers
Classifier: Programming Language :: Python :: 2.6
Classifier: Programming Language :: Python :: 2.7
Classifier: Programming Language :: Python :: 3.3
Classifier: Programming Language :: Python :: 3.4
Classifier: Programming Language :: Python :: 3.5
Classifier: Programming Language :: Python :: 3.6
